{
    "chain_name": "og-testnet",
    "chain_id": "",
    "api": ["https://og-testnet-api.itrocket.net"],
    "rpc": ["https://og-testnet-rpc.itrocket.net"],
    "coingecko": "",
    "snapshot_provider": "",
    "sdk_version": "0.47.1",
    "coin_type": "118",
    "min_tx_fee": "500",
    "addr_prefix": "0g",
    "logo": "https://imgur.com/cgdmv8K.jpg",
    "assets": [{
        "base": "ua0gi",
        "symbol": "a0gi",
        "exponent": "6",
        "coingecko_id": "",
        "logo": "https://imgur.com/cgdmv8K.jpg"
    }]
  }